src/__init__.py
src/__main__.py
sparckles-0.1.0.dist-info/METADATA
sparckles-0.1.0.dist-info/WHEEL
sparckles-0.1.0.dist-info/RECORD
